{
  "attn": "centroid",
  "gate": true,
  "route_lambda": 1.0,
  "balance_lambda": 0.0,
  "history": [
    {
      "step": 0,
      "loss": 4.365,
      "acc": 0.0,
      "hit": 0.1016,
      "route": 8.4992,
      "pairs": 2,
      "sec": 1.1
    },
    {
      "step": 200,
      "loss": 4.0969,
      "acc": 0.0469,
      "hit": 1.0,
      "route": 3.9615,
      "pairs": 2,
      "sec": 42.7
    },
    {
      "step": 400,
      "loss": 1.1014,
      "acc": 0.5938,
      "hit": 1.0,
      "route": 3.3323,
      "pairs": 2,
      "sec": 84.2
    },
    {
      "step": 600,
      "loss": 1.1074,
      "acc": 0.5469,
      "hit": 1.0,
      "route": 3.3433,
      "pairs": 2,
      "sec": 125.8
    },
    {
      "step": 800,
      "loss": 0.8844,
      "acc": 0.5781,
      "hit": 1.0,
      "route": 3.3383,
      "pairs": 2,
      "sec": 167.3
    },
    {
      "step": 1000,
      "loss": 1.6673,
      "acc": 0.2969,
      "hit": 1.0,
      "route": 4.0928,
      "pairs": 3,
      "sec": 209.2
    },
    {
      "step": 1200,
      "loss": 1.5415,
      "acc": 0.3438,
      "hit": 1.0,
      "route": 4.0928,
      "pairs": 3,
      "sec": 251.1
    },
    {
      "step": 1400,
      "loss": 1.3475,
      "acc": 0.3906,
      "hit": 1.0,
      "route": 4.0424,
      "pairs": 3,
      "sec": 293.0
    },
    {
      "step": 1600,
      "loss": 1.6264,
      "acc": 0.2812,
      "hit": 1.0,
      "route": 4.0802,
      "pairs": 3,
      "sec": 335.0
    },
    {
      "step": 1800,
      "loss": 2.0459,
      "acc": 0.125,
      "hit": 1.0,
      "route": 4.621,
      "pairs": 4,
      "sec": 377.1
    },
    {
      "step": 2000,
      "loss": 1.7459,
      "acc": 0.2188,
      "hit": 1.0,
      "route": 4.5986,
      "pairs": 4,
      "sec": 419.4
    },
    {
      "step": 2200,
      "loss": 1.784,
      "acc": 0.3438,
      "hit": 1.0,
      "route": 4.5753,
      "pairs": 4,
      "sec": 461.7
    },
    {
      "step": 2400,
      "loss": 1.7574,
      "acc": 0.2656,
      "hit": 1.0,
      "route": 4.5724,
      "pairs": 4,
      "sec": 504.0
    },
    {
      "step": 2600,
      "loss": 1.9477,
      "acc": 0.2031,
      "hit": 1.0,
      "route": 5.0802,
      "pairs": 5,
      "sec": 546.5
    },
    {
      "step": 2800,
      "loss": 1.8601,
      "acc": 0.25,
      "hit": 1.0,
      "route": 5.1357,
      "pairs": 5,
      "sec": 589.1
    },
    {
      "step": 3000,
      "loss": 1.9736,
      "acc": 0.1875,
      "hit": 1.0,
      "route": 4.9581,
      "pairs": 5,
      "sec": 631.7
    },
    {
      "step": 3200,
      "loss": 1.7065,
      "acc": 0.2812,
      "hit": 1.0,
      "route": 5.0464,
      "pairs": 5,
      "sec": 674.3
    },
    {
      "step": 3400,
      "loss": 1.8913,
      "acc": 0.2812,
      "hit": 0.9766,
      "route": 5.5935,
      "pairs": 6,
      "sec": 717.0
    },
    {
      "step": 3600,
      "loss": 1.9853,
      "acc": 0.2344,
      "hit": 1.0,
      "route": 5.444,
      "pairs": 6,
      "sec": 759.9
    },
    {
      "step": 3800,
      "loss": 1.9025,
      "acc": 0.2188,
      "hit": 1.0,
      "route": 5.4537,
      "pairs": 6,
      "sec": 802.8
    },
    {
      "step": 4000,
      "loss": 2.0682,
      "acc": 0.2188,
      "hit": 1.0,
      "route": 5.3776,
      "pairs": 6,
      "sec": 845.8
    },
    {
      "step": 4200,
      "loss": 2.205,
      "acc": 0.1562,
      "hit": 1.0,
      "route": 5.7318,
      "pairs": 7,
      "sec": 888.8
    },
    {
      "step": 4400,
      "loss": 2.1354,
      "acc": 0.2344,
      "hit": 1.0,
      "route": 5.688,
      "pairs": 7,
      "sec": 932.1
    },
    {
      "step": 4600,
      "loss": 2.0368,
      "acc": 0.2031,
      "hit": 1.0,
      "route": 5.7287,
      "pairs": 7,
      "sec": 975.4
    },
    {
      "step": 4800,
      "loss": 2.1973,
      "acc": 0.1719,
      "hit": 1.0,
      "route": 5.7415,
      "pairs": 7,
      "sec": 1018.7
    },
    {
      "step": 5000,
      "loss": 2.2872,
      "acc": 0.1406,
      "hit": 1.0,
      "route": 5.8952,
      "pairs": 8,
      "sec": 1062.0
    },
    {
      "step": 5200,
      "loss": 2.3086,
      "acc": 0.125,
      "hit": 1.0,
      "route": 5.9935,
      "pairs": 8,
      "sec": 1105.7
    },
    {
      "step": 5400,
      "loss": 2.2446,
      "acc": 0.2344,
      "hit": 1.0,
      "route": 5.9576,
      "pairs": 8,
      "sec": 1149.3
    },
    {
      "step": 5600,
      "loss": 2.4021,
      "acc": 0.1094,
      "hit": 1.0,
      "route": 5.98,
      "pairs": 8,
      "sec": 1192.9
    },
    {
      "step": 5800,
      "loss": 2.4052,
      "acc": 0.125,
      "hit": 1.0,
      "route": 6.0103,
      "pairs": 8,
      "sec": 1236.5
    },
    {
      "step": 6000,
      "loss": 2.2342,
      "acc": 0.2031,
      "hit": 1.0,
      "route": 5.9905,
      "pairs": 8,
      "sec": 1280.1
    },
    {
      "step": 6200,
      "loss": 2.1689,
      "acc": 0.1719,
      "hit": 1.0,
      "route": 5.9181,
      "pairs": 8,
      "sec": 1323.8
    },
    {
      "step": 6400,
      "loss": 2.2593,
      "acc": 0.1719,
      "hit": 1.0,
      "route": 5.9955,
      "pairs": 8,
      "sec": 1367.4
    },
    {
      "step": 6600,
      "loss": 2.2026,
      "acc": 0.1562,
      "hit": 1.0,
      "route": 5.9989,
      "pairs": 8,
      "sec": 1411.0
    },
    {
      "step": 6800,
      "loss": 2.0981,
      "acc": 0.2188,
      "hit": 1.0,
      "route": 5.8967,
      "pairs": 8,
      "sec": 1454.6
    },
    {
      "step": 7000,
      "loss": 2.2267,
      "acc": 0.1875,
      "hit": 1.0,
      "route": 5.9097,
      "pairs": 8,
      "sec": 1498.2
    },
    {
      "step": 7200,
      "loss": 2.0797,
      "acc": 0.2188,
      "hit": 1.0,
      "route": 5.9832,
      "pairs": 8,
      "sec": 1541.8
    },
    {
      "step": 7400,
      "loss": 2.043,
      "acc": 0.1875,
      "hit": 1.0,
      "route": 5.9486,
      "pairs": 8,
      "sec": 1585.5
    },
    {
      "step": 7600,
      "loss": 2.1497,
      "acc": 0.1406,
      "hit": 1.0,
      "route": 5.9946,
      "pairs": 8,
      "sec": 1629.1
    },
    {
      "step": 7800,
      "loss": 2.2427,
      "acc": 0.0781,
      "hit": 1.0,
      "route": 5.9526,
      "pairs": 8,
      "sec": 1672.7
    },
    {
      "step": 8000,
      "loss": 2.2331,
      "acc": 0.0781,
      "hit": 1.0,
      "route": 5.9055,
      "pairs": 8,
      "sec": 1716.3
    },
    {
      "step": 8200,
      "loss": 2.1649,
      "acc": 0.1875,
      "hit": 1.0,
      "route": 6.0297,
      "pairs": 8,
      "sec": 1759.9
    },
    {
      "step": 8400,
      "loss": 2.1075,
      "acc": 0.1562,
      "hit": 1.0,
      "route": 5.9463,
      "pairs": 8,
      "sec": 1803.5
    },
    {
      "step": 8600,
      "loss": 2.2499,
      "acc": 0.0938,
      "hit": 1.0,
      "route": 5.9921,
      "pairs": 8,
      "sec": 1847.2
    },
    {
      "step": 8800,
      "loss": 2.119,
      "acc": 0.1875,
      "hit": 1.0,
      "route": 5.952,
      "pairs": 8,
      "sec": 1890.8
    },
    {
      "step": 9000,
      "loss": 2.1783,
      "acc": 0.1875,
      "hit": 1.0,
      "route": 6.009,
      "pairs": 8,
      "sec": 1934.4
    },
    {
      "step": 9200,
      "loss": 2.1054,
      "acc": 0.1562,
      "hit": 1.0,
      "route": 5.9641,
      "pairs": 8,
      "sec": 1978.0
    },
    {
      "step": 9400,
      "loss": 2.1232,
      "acc": 0.2031,
      "hit": 1.0,
      "route": 6.0165,
      "pairs": 8,
      "sec": 2021.6
    },
    {
      "step": 9600,
      "loss": 2.165,
      "acc": 0.1562,
      "hit": 1.0,
      "route": 5.9616,
      "pairs": 8,
      "sec": 2065.2
    },
    {
      "step": 9800,
      "loss": 2.1408,
      "acc": 0.1406,
      "hit": 1.0,
      "route": 5.9081,
      "pairs": 8,
      "sec": 2108.9
    },
    {
      "step": 9999,
      "loss": 2.1614,
      "acc": 0.1719,
      "hit": 1.0,
      "route": 5.9404,
      "pairs": 8,
      "sec": 2152.3
    }
  ],
  "final_acc": 0.1748,
  "final_hit": 1.0,
  "refine_acc": 0.1533,
  "refine_hit": 0.7295
}